{
  "db_name": "PostgreSQL",
  "query": "INSERT INTO rocket_sensor_gps_vel\n        (rocket_sensor_message_id, time_stamp, status, time_of_week, velocity, velocity_acc, course, course_acc)\n        VALUES ($1, $2, $3, $4, $5, $6, $7, $8)",
  "describe": {
    "columns": [],
    "parameters": {
      "Left": [
        "Int4",
        "Int4",
        "Int4",
        "Int4",
        "Int4",
        "Int4",
        "Float4",
        "Float4"
      ]
    },
    "nullable": []
  },
  "hash": "c2eb1b9a4e661d432cb2dbe9cc0e53c7736a2808eef2471478785f86cfbe250a"
}
